chinese_nonwords/__init__.py
chinese_nonwords/example.py
chinese_nonwords/data/subset.csv
chinese_nonwords/data/word.csv
chinese_nonwords-0.0.19.dist-info/METADATA
chinese_nonwords-0.0.19.dist-info/WHEEL
chinese_nonwords-0.0.19.dist-info/licenses/LICENSE
chinese_nonwords-0.0.19.dist-info/RECORD
