Metadata-Version: 2.1
Name: chinese-nonwords
Version: 0.0.19
Summary:  package for generating Chinese disyllabic nonwords
Project-URL: Homepage, https://github.com/zimine/Chinese-nonwords-generator
Project-URL: Issues, https://github.com/zimine/Chinese-nonwords-generator
Author-email: Mingyu <author@example.com>
License-File: LICENSE
Classifier: License :: OSI Approved :: MIT License
Classifier: Operating System :: OS Independent
Classifier: Programming Language :: Python :: 3
Requires-Python: >=3.7
Requires-Dist: pypinyin>=0.50.0
Requires-Dist: tabulate>=0.9.0
